{
  "project_info": {
    "project_number": "879820637627",
    "project_id": "lolcustom-3d471",
    "storage_bucket": "lolcustom-3d471.firebasestorage.app"
  },
  "client": [
    {
      "client_info": {
        "mobilesdk_app_id": "1:879820637627:android:e6887083fc59a9d3c9709e",
        "android_client_info": {
          "package_name": "com.example.lol_custom_game_manager"
        }
      },
      "oauth_client": [],
      "api_key": [
        {
          "current_key": "AIzaSyB7iVwjLVb_TB0P_tBJAU57KmUu3Yq-Dss"
        }
      ],
      "services": {
        "appinvite_service": {
          "other_platform_oauth_client": []
        }
      }
    },
    {
      "client_info": {
        "mobilesdk_app_id": "1:879820637627:android:3eba3fdbc1aa01c1c9709e",
        "android_client_info": {
          "package_name": "com.judgg.lolcustom"
        }
      },
      "oauth_client": [],
      "api_key": [
        {
          "current_key": "AIzaSyB7iVwjLVb_TB0P_tBJAU57KmUu3Yq-Dss"
        }
      ],
      "services": {
        "appinvite_service": {
          "other_platform_oauth_client": []
        }
      }
    }
  ],
  "configuration_version": "1"
}